{
    "mainBn1":[
        {"src": "./img/main/main1-1.jpg"},
        {"src": "./img/main/main1-2.jpg"},
        {"src": "./img/main/main1-3.jpg"}
    ],
    "mainBn2":[
        {"src": "./img/main/main2-1.jpg"},
        {"src": "./img/main/main2-2.jpg"}
    ],
    "goodslist1":[
        {"thum":"./img/newcollection/new1.jpg", "src":"", "name":"NSAD* THINDOWN HOODY JACKET 01", "price":"329000"},
        {"thum":"./img/newcollection/new2.jpg", "src":"", "name":"NSAD* THINDOWN HOODY JACKET 02", "price":"459000"},
        {"thum":"./img/newcollection/new3.jpg", "src":"", "name":"NSAD* THINDOWN HOODY JACKET 03", "price":"329000"},
        {"thum":"./img/newcollection/new4.jpg", "src":"", "name":"NSAD* THINDOWN HOODY JACKET 04", "price":"559000"},
        {"thum":"./img/newcollection/new5.jpg", "src":"", "name":"NSAD* THINDOWN HOODY JACKET 05", "price":"329000"},
        {"thum":"./img/newcollection/new6.jpg", "src":"", "name":"NSAD* THINDOWN HOODY JACKET 06", "price":"459000"},
        {"thum":"./img/newcollection/new7.jpg", "src":"", "name":"NSAD* THINDOWN HOODY JACKET 07", "price":"329000"},
        {"thum":"./img/newcollection/new8.jpg", "src":"", "name":"NSAD* THINDOWN HOODY JACKET 08", "price":"559000"},
        {"thum":"./img/newcollection/new9.jpg", "src":"", "name":"NSAD* THINDOWN HOODY JACKET 09", "price":"559000"},
        {"thum":"./img/newcollection/new10.jpg", "src":"", "name":"NSAD* THINDOWN HOODY JACKET 10", "price":"329000"},
        {"thum":"./img/newcollection/new11.jpg", "src":"", "name":"NSAD* THINDOWN HOODY JACKET 11", "price":"559000"},
        {"thum":"./img/newcollection/new12.jpg", "src":"", "name":"NSAD* THINDOWN HOODY JACKET 12", "price":"459000"},
        {"thum":"./img/newcollection/new13.jpg", "src":"", "name":"NSAD* THINDOWN HOODY JACKET 13", "price":"329000"},
        {"thum":"./img/newcollection/new14.jpg", "src":"", "name":"NSAD* THINDOWN HOODY JACKET 14", "price":"559000"},
        {"thum":"./img/newcollection/new15.jpg", "src":"", "name":"NSAD* THINDOWN HOODY JACKET 15", "price":"559000"},
        {"thum":"./img/newcollection/new16.jpg", "src":"", "name":"NSAD* THINDOWN HOODY JACKET 16", "price":"329000"},
        {"thum":"./img/newcollection/new17.jpg", "src":"", "name":"NSAD* THINDOWN HOODY JACKET 17", "price":"459000"},
        {"thum":"./img/newcollection/new18.jpg", "src":"", "name":"NSAD* THINDOWN HOODY JACKET 18", "price":"559000"},
        {"thum":"./img/newcollection/new19.jpg", "src":"", "name":"NSAD* THINDOWN HOODY JACKET 19", "price":"329000"},
        {"thum":"./img/newcollection/new20.jpg", "src":"", "name":"NSAD* THINDOWN HOODY JACKET 20", "price":"459000"},
        {"thum":"./img/newcollection/new21.jpg", "src":"", "name":"NSAD* THINDOWN HOODY JACKET 21", "price":"559000"},
        {"thum":"./img/newcollection/new22.jpg", "src":"", "name":"NSAD* THINDOWN HOODY JACKET 22", "price":"329000"},
        {"thum":"./img/newcollection/new23.jpg", "src":"", "name":"NSAD* THINDOWN HOODY JACKET 23", "price":"459000"},
        {"thum":"./img/newcollection/new24.jpg", "src":"", "name":"NSAD* THINDOWN HOODY JACKET 24", "price":"559000"},
        {"thum":"./img/newcollection/new25.jpg", "src":"", "name":"NSAD* THINDOWN HOODY JACKET 25", "price":"329000"},
        {"thum":"./img/newcollection/new26.jpg", "src":"", "name":"NSAD* THINDOWN HOODY JACKET 26", "price":"459000"},
        {"thum":"./img/newcollection/new27.jpg", "src":"", "name":"NSAD* THINDOWN HOODY JACKET 27", "price":"559000"},
        {"thum":"./img/newcollection/new28.jpg", "src":"", "name":"NSAD* THINDOWN HOODY JACKET 28", "price":"329000"}
    ],
    "goodsdetail1":[
        {"baner1":"./img/goodsdetail/item01/new1_detail_01.jpg",
        "baner2":"./img/goodsdetail/item01/new1_detail_02.jpg",
        "detail1":"./img/goodsdetail/item01/new1_detail_03.jpg",
        "detail2":"./img/goodsdetail/item01/new1_detail_04.jpg",
        "detail3":"./img/goodsdetail/item01/new1_detail_05.jpg",
        "detail4":"./img/goodsdetail/item01/new1_detail_06.jpg",
        "detail5":"./img/goodsdetail/item01/new1_detail_07.jpg",
        "detail6":"./img/goodsdetail/item01/new1_detail_08.jpg",
        "detail7":"./img/goodsdetail/item01/new1_detail_09.jpg",
        "detail8":"./img/goodsdetail/item01/new1_detail_10.jpg"},

        {"baner1":"./img/goodsdetail/item02/new1_detail_01.jpg",
        "baner2":"./img/goodsdetail/item02/new1_detail_02.jpg",
        "detail1":"./img/goodsdetail/item02/new1_detail_03.jpg",
        "detail2":"./img/goodsdetail/item02/new1_detail_04.jpg",
        "detail3":"./img/goodsdetail/item02/new1_detail_05.jpg",
        "detail4":"./img/goodsdetail/item02/new1_detail_06.jpg",
        "detail5":"./img/goodsdetail/item02/new1_detail_07.jpg",
        "detail6":"./img/goodsdetail/item02/new1_detail_08.jpg",
        "detail7":"./img/goodsdetail/item02/new1_detail_09.jpg",
        "detail8":"./img/goodsdetail/item02/new1_detail_10.jpg"},

        {"baner1":"./img/goodsdetail/item03/new1_detail_01.jpg",
        "baner2":"./img/goodsdetail/item03/new1_detail_02.jpg",
        "detail1":"./img/goodsdetail/item03/new1_detail_03.jpg",
        "detail2":"./img/goodsdetail/item03/new1_detail_04.jpg",
        "detail3":"./img/goodsdetail/item03/new1_detail_05.jpg",
        "detail4":"./img/goodsdetail/item03/new1_detail_06.jpg",
        "detail5":"./img/goodsdetail/item03/new1_detail_07.jpg",
        "detail6":"./img/goodsdetail/item03/new1_detail_08.jpg",
        "detail7":"./img/goodsdetail/item03/new1_detail_09.jpg",
        "detail8":"./img/goodsdetail/item03/new1_detail_10.jpg"},

        {"baner1":"./img/goodsdetail/item04/new1_detail_01.jpg",
        "baner2":"./img/goodsdetail/item04/new1_detail_02.jpg",
        "detail1":"./img/goodsdetail/item04/new1_detail_03.jpg",
        "detail2":"./img/goodsdetail/item04/new1_detail_04.jpg",
        "detail3":"./img/goodsdetail/item04/new1_detail_05.jpg",
        "detail4":"./img/goodsdetail/item04/new1_detail_06.jpg",
        "detail5":"./img/goodsdetail/item04/new1_detail_07.jpg",
        "detail6":"./img/goodsdetail/item04/new1_detail_08.jpg",
        "detail7":"./img/goodsdetail/item04/new1_detail_09.jpg",
        "detail8":"./img/goodsdetail/item04/new1_detail_10.jpg"},

        {"baner1":"./img/goodsdetail/item05/new1_detail_01.jpg",
        "baner2":"./img/goodsdetail/item05/new1_detail_02.jpg",
        "detail1":"./img/goodsdetail/item05/new1_detail_03.jpg",
        "detail2":"./img/goodsdetail/item05/new1_detail_04.jpg",
        "detail3":"./img/goodsdetail/item05/new1_detail_05.jpg",
        "detail4":"./img/goodsdetail/item05/new1_detail_06.jpg",
        "detail5":"./img/goodsdetail/item05/new1_detail_07.jpg",
        "detail6":"./img/goodsdetail/item05/new1_detail_08.jpg",
        "detail7":"./img/goodsdetail/item05/new1_detail_09.jpg",
        "detail8":"./img/goodsdetail/item05/new1_detail_10.jpg"},

        {"baner1":"./img/goodsdetail/item06/new1_detail_01.jpg",
        "baner2":"./img/goodsdetail/item06/new1_detail_02.jpg",
        "detail1":"./img/goodsdetail/item06/new1_detail_03.jpg",
        "detail2":"./img/goodsdetail/item06/new1_detail_04.jpg",
        "detail3":"./img/goodsdetail/item06/new1_detail_05.jpg",
        "detail4":"./img/goodsdetail/item06/new1_detail_06.jpg",
        "detail5":"./img/goodsdetail/item06/new1_detail_07.jpg",
        "detail6":"./img/goodsdetail/item06/new1_detail_08.jpg",
        "detail7":"./img/goodsdetail/item06/new1_detail_09.jpg",
        "detail8":"./img/goodsdetail/item06/new1_detail_10.jpg"},

        {"baner1":"./img/goodsdetail/item07/new1_detail_01.jpg",
        "baner2":"./img/goodsdetail/item07/new1_detail_02.jpg",
        "detail1":"./img/goodsdetail/item07/new1_detail_03.jpg",
        "detail2":"./img/goodsdetail/item07/new1_detail_04.jpg",
        "detail3":"./img/goodsdetail/item07/new1_detail_05.jpg",
        "detail4":"./img/goodsdetail/item07/new1_detail_06.jpg",
        "detail5":"./img/goodsdetail/item07/new1_detail_07.jpg",
        "detail6":"./img/goodsdetail/item07/new1_detail_08.jpg",
        "detail7":"./img/goodsdetail/item07/new1_detail_09.jpg",
        "detail8":"./img/goodsdetail/item07/new1_detail_10.jpg"},

        {"baner1":"./img/goodsdetail/item08/new1_detail_01.jpg",
        "baner2":"./img/goodsdetail/item08/new1_detail_02.jpg",
        "detail1":"./img/goodsdetail/item08/new1_detail_03.jpg",
        "detail2":"./img/goodsdetail/item08/new1_detail_04.jpg",
        "detail3":"./img/goodsdetail/item08/new1_detail_05.jpg",
        "detail4":"./img/goodsdetail/item08/new1_detail_06.jpg",
        "detail5":"./img/goodsdetail/item08/new1_detail_07.jpg",
        "detail6":"./img/goodsdetail/item08/new1_detail_08.jpg",
        "detail7":"./img/goodsdetail/item08/new1_detail_09.jpg",
        "detail8":"./img/goodsdetail/item08/new1_detail_10.jpg"},

        {"baner1":"./img/goodsdetail/item09/new1_detail_01.jpg",
        "baner2":"./img/goodsdetail/item09/new1_detail_02.jpg",
        "detail1":"./img/goodsdetail/item09/new1_detail_03.jpg",
        "detail2":"./img/goodsdetail/item09/new1_detail_04.jpg",
        "detail3":"./img/goodsdetail/item09/new1_detail_05.jpg",
        "detail4":"./img/goodsdetail/item09/new1_detail_06.jpg",
        "detail5":"./img/goodsdetail/item09/new1_detail_07.jpg",
        "detail6":"./img/goodsdetail/item09/new1_detail_08.jpg",
        "detail7":"./img/goodsdetail/item09/new1_detail_09.jpg",
        "detail8":"./img/goodsdetail/item09/new1_detail_10.jpg"},

        {"baner1":"./img/goodsdetail/item10/new1_detail_01.jpg",
        "baner2":"./img/goodsdetail/item10/new1_detail_02.jpg",
        "detail1":"./img/goodsdetail/item10/new1_detail_03.jpg",
        "detail2":"./img/goodsdetail/item10/new1_detail_04.jpg",
        "detail3":"./img/goodsdetail/item10/new1_detail_05.jpg",
        "detail4":"./img/goodsdetail/item10/new1_detail_06.jpg",
        "detail5":"./img/goodsdetail/item10/new1_detail_07.jpg",
        "detail6":"./img/goodsdetail/item10/new1_detail_08.jpg",
        "detail7":"./img/goodsdetail/item10/new1_detail_09.jpg",
        "detail8":"./img/goodsdetail/item10/new1_detail_10.jpg"},

        {"baner1":"./img/goodsdetail/item11/new1_detail_01.jpg",
        "baner2":"./img/goodsdetail/item11/new1_detail_02.jpg",
        "detail1":"./img/goodsdetail/item11/new1_detail_03.jpg",
        "detail2":"./img/goodsdetail/item11/new1_detail_04.jpg",
        "detail3":"./img/goodsdetail/item11/new1_detail_05.jpg",
        "detail4":"./img/goodsdetail/item11/new1_detail_06.jpg",
        "detail5":"./img/goodsdetail/item11/new1_detail_07.jpg",
        "detail6":"./img/goodsdetail/item11/new1_detail_08.jpg",
        "detail7":"./img/goodsdetail/item11/new1_detail_09.jpg",
        "detail8":"./img/goodsdetail/item11/new1_detail_10.jpg"},

        {"baner1":"./img/goodsdetail/item12/new1_detail_01.jpg",
        "baner2":"./img/goodsdetail/item12/new1_detail_02.jpg",
        "detail1":"./img/goodsdetail/item12/new1_detail_03.jpg",
        "detail2":"./img/goodsdetail/item12/new1_detail_04.jpg",
        "detail3":"./img/goodsdetail/item12/new1_detail_05.jpg",
        "detail4":"./img/goodsdetail/item12/new1_detail_06.jpg",
        "detail5":"./img/goodsdetail/item12/new1_detail_07.jpg",
        "detail6":"./img/goodsdetail/item12/new1_detail_08.jpg",
        "detail7":"./img/goodsdetail/item12/new1_detail_09.jpg",
        "detail8":"./img/goodsdetail/item12/new1_detail_10.jpg"},

        {"baner1":"./img/goodsdetail/item13/new1_detail_01.jpg",
        "baner2":"./img/goodsdetail/item13/new1_detail_02.jpg",
        "detail1":"./img/goodsdetail/item13/new1_detail_03.jpg",
        "detail2":"./img/goodsdetail/item13/new1_detail_04.jpg",
        "detail3":"./img/goodsdetail/item13/new1_detail_05.jpg",
        "detail4":"./img/goodsdetail/item13/new1_detail_06.jpg",
        "detail5":"./img/goodsdetail/item13/new1_detail_07.jpg",
        "detail6":"./img/goodsdetail/item13/new1_detail_08.jpg",
        "detail7":"./img/goodsdetail/item13/new1_detail_09.jpg",
        "detail8":"./img/goodsdetail/item13/new1_detail_10.jpg"},

        {"baner1":"./img/goodsdetail/item14/new1_detail_01.jpg",
        "baner2":"./img/goodsdetail/item14/new1_detail_02.jpg",
        "detail1":"./img/goodsdetail/item14/new1_detail_03.jpg",
        "detail2":"./img/goodsdetail/item14/new1_detail_04.jpg",
        "detail3":"./img/goodsdetail/item14/new1_detail_05.jpg",
        "detail4":"./img/goodsdetail/item14/new1_detail_06.jpg",
        "detail5":"./img/goodsdetail/item14/new1_detail_07.jpg",
        "detail6":"./img/goodsdetail/item14/new1_detail_08.jpg",
        "detail7":"./img/goodsdetail/item14/new1_detail_09.jpg",
        "detail8":"./img/goodsdetail/item14/new1_detail_10.jpg"},

        {"baner1":"./img/goodsdetail/item15/new1_detail_01.jpg",
        "baner2":"./img/goodsdetail/item15/new1_detail_02.jpg",
        "detail1":"./img/goodsdetail/item15/new1_detail_03.jpg",
        "detail2":"./img/goodsdetail/item15/new1_detail_04.jpg",
        "detail3":"./img/goodsdetail/item15/new1_detail_05.jpg",
        "detail4":"./img/goodsdetail/item15/new1_detail_06.jpg",
        "detail5":"./img/goodsdetail/item15/new1_detail_07.jpg",
        "detail6":"./img/goodsdetail/item15/new1_detail_08.jpg",
        "detail7":"./img/goodsdetail/item15/new1_detail_09.jpg",
        "detail8":"./img/goodsdetail/item15/new1_detail_10.jpg"},

        {"baner1":"./img/goodsdetail/item16/new1_detail_01.jpg",
        "baner2":"./img/goodsdetail/item16/new1_detail_02.jpg",
        "detail1":"./img/goodsdetail/item16/new1_detail_03.jpg",
        "detail2":"./img/goodsdetail/item16/new1_detail_04.jpg",
        "detail3":"./img/goodsdetail/item16/new1_detail_05.jpg",
        "detail4":"./img/goodsdetail/item16/new1_detail_06.jpg",
        "detail5":"./img/goodsdetail/item16/new1_detail_07.jpg",
        "detail6":"./img/goodsdetail/item16/new1_detail_08.jpg",
        "detail7":"./img/goodsdetail/item16/new1_detail_09.jpg",
        "detail8":"./img/goodsdetail/item16/new1_detail_10.jpg"},

        {"baner1":"./img/goodsdetail/item17/new1_detail_01.jpg",
        "baner2":"./img/goodsdetail/item17/new1_detail_02.jpg",
        "detail1":"./img/goodsdetail/item17/new1_detail_03.jpg",
        "detail2":"./img/goodsdetail/item17/new1_detail_04.jpg",
        "detail3":"./img/goodsdetail/item17/new1_detail_05.jpg",
        "detail4":"./img/goodsdetail/item17/new1_detail_06.jpg",
        "detail5":"./img/goodsdetail/item17/new1_detail_07.jpg",
        "detail6":"./img/goodsdetail/item17/new1_detail_08.jpg",
        "detail7":"./img/goodsdetail/item17/new1_detail_09.jpg",
        "detail8":"./img/goodsdetail/item17/new1_detail_10.jpg"},

        {"baner1":"./img/goodsdetail/item18/new1_detail_01.jpg",
        "baner2":"./img/goodsdetail/item18/new1_detail_02.jpg",
        "detail1":"./img/goodsdetail/item18/new1_detail_03.jpg",
        "detail2":"./img/goodsdetail/item18/new1_detail_04.jpg",
        "detail3":"./img/goodsdetail/item18/new1_detail_05.jpg",
        "detail4":"./img/goodsdetail/item18/new1_detail_06.jpg",
        "detail5":"./img/goodsdetail/item18/new1_detail_07.jpg",
        "detail6":"./img/goodsdetail/item18/new1_detail_08.jpg",
        "detail7":"./img/goodsdetail/item18/new1_detail_09.jpg",
        "detail8":"./img/goodsdetail/item18/new1_detail_10.jpg"},

        {"baner1":"./img/goodsdetail/item19/new1_detail_01.jpg",
        "baner2":"./img/goodsdetail/item19/new1_detail_02.jpg",
        "detail1":"./img/goodsdetail/item19/new1_detail_03.jpg",
        "detail2":"./img/goodsdetail/item19/new1_detail_04.jpg",
        "detail3":"./img/goodsdetail/item19/new1_detail_05.jpg",
        "detail4":"./img/goodsdetail/item19/new1_detail_06.jpg",
        "detail5":"./img/goodsdetail/item19/new1_detail_07.jpg",
        "detail6":"./img/goodsdetail/item19/new1_detail_08.jpg",
        "detail7":"./img/goodsdetail/item19/new1_detail_09.jpg",
        "detail8":"./img/goodsdetail/item19/new1_detail_10.jpg"},

        {"baner1":"./img/goodsdetail/item20/new1_detail_01.jpg",
        "baner2":"./img/goodsdetail/item20/new1_detail_02.jpg",
        "detail1":"./img/goodsdetail/item20/new1_detail_03.jpg",
        "detail2":"./img/goodsdetail/item20/new1_detail_04.jpg",
        "detail3":"./img/goodsdetail/item20/new1_detail_05.jpg",
        "detail4":"./img/goodsdetail/item20/new1_detail_06.jpg",
        "detail5":"./img/goodsdetail/item20/new1_detail_07.jpg",
        "detail6":"./img/goodsdetail/item20/new1_detail_08.jpg",
        "detail7":"./img/goodsdetail/item20/new1_detail_09.jpg",
        "detail8":"./img/goodsdetail/item20/new1_detail_10.jpg"},

        {"baner1":"./img/goodsdetail/item21/new1_detail_01.jpg",
        "baner2":"./img/goodsdetail/item21/new1_detail_02.jpg",
        "detail1":"./img/goodsdetail/item21/new1_detail_03.jpg",
        "detail2":"./img/goodsdetail/item21/new1_detail_04.jpg",
        "detail3":"./img/goodsdetail/item21/new1_detail_05.jpg",
        "detail4":"./img/goodsdetail/item21/new1_detail_06.jpg",
        "detail5":"./img/goodsdetail/item21/new1_detail_07.jpg",
        "detail6":"./img/goodsdetail/item21/new1_detail_08.jpg",
        "detail7":"./img/goodsdetail/item21/new1_detail_09.jpg",
        "detail8":"./img/goodsdetail/item21/new1_detail_10.jpg"},

        {"baner1":"./img/goodsdetail/item22/new1_detail_01.jpg",
        "baner2":"./img/goodsdetail/item22/new1_detail_02.jpg",
        "detail1":"./img/goodsdetail/item22/new1_detail_03.jpg",
        "detail2":"./img/goodsdetail/item22/new1_detail_04.jpg",
        "detail3":"./img/goodsdetail/item22/new1_detail_05.jpg",
        "detail4":"./img/goodsdetail/item22/new1_detail_06.jpg",
        "detail5":"./img/goodsdetail/item22/new1_detail_07.jpg",
        "detail6":"./img/goodsdetail/item22/new1_detail_08.jpg",
        "detail7":"./img/goodsdetail/item22/new1_detail_09.jpg",
        "detail8":"./img/goodsdetail/item22/new1_detail_10.jpg"},

        {"baner1":"./img/goodsdetail/item23/new1_detail_01.jpg",
        "baner2":"./img/goodsdetail/item23/new1_detail_02.jpg",
        "detail1":"./img/goodsdetail/item23/new1_detail_03.jpg",
        "detail2":"./img/goodsdetail/item23/new1_detail_04.jpg",
        "detail3":"./img/goodsdetail/item23/new1_detail_05.jpg",
        "detail4":"./img/goodsdetail/item23/new1_detail_06.jpg",
        "detail5":"./img/goodsdetail/item23/new1_detail_07.jpg",
        "detail6":"./img/goodsdetail/item23/new1_detail_08.jpg",
        "detail7":"./img/goodsdetail/item23/new1_detail_09.jpg",
        "detail8":"./img/goodsdetail/item23/new1_detail_10.jpg"},

        {"baner1":"./img/goodsdetail/item24/new1_detail_01.jpg",
        "baner2":"./img/goodsdetail/item24/new1_detail_02.jpg",
        "detail1":"./img/goodsdetail/item24/new1_detail_03.jpg",
        "detail2":"./img/goodsdetail/item24/new1_detail_04.jpg",
        "detail3":"./img/goodsdetail/item24/new1_detail_05.jpg",
        "detail4":"./img/goodsdetail/item24/new1_detail_06.jpg",
        "detail5":"./img/goodsdetail/item24/new1_detail_07.jpg",
        "detail6":"./img/goodsdetail/item24/new1_detail_08.jpg",
        "detail7":"./img/goodsdetail/item24/new1_detail_09.jpg",
        "detail8":"./img/goodsdetail/item24/new1_detail_10.jpg"},

        {"baner1":"./img/goodsdetail/item25/new1_detail_01.jpg",
        "baner2":"./img/goodsdetail/item25/new1_detail_02.jpg",
        "detail1":"./img/goodsdetail/item25/new1_detail_03.jpg",
        "detail2":"./img/goodsdetail/item25/new1_detail_04.jpg",
        "detail3":"./img/goodsdetail/item25/new1_detail_05.jpg",
        "detail4":"./img/goodsdetail/item25/new1_detail_06.jpg",
        "detail5":"./img/goodsdetail/item25/new1_detail_07.jpg",
        "detail6":"./img/goodsdetail/item25/new1_detail_08.jpg",
        "detail7":"./img/goodsdetail/item25/new1_detail_09.jpg",
        "detail8":"./img/goodsdetail/item25/new1_detail_10.jpg"},

        {"baner1":"./img/goodsdetail/item26/new1_detail_01.jpg",
        "baner2":"./img/goodsdetail/item26/new1_detail_02.jpg",
        "detail1":"./img/goodsdetail/item26/new1_detail_03.jpg",
        "detail2":"./img/goodsdetail/item26/new1_detail_04.jpg",
        "detail3":"./img/goodsdetail/item26/new1_detail_05.jpg",
        "detail4":"./img/goodsdetail/item26/new1_detail_06.jpg",
        "detail5":"./img/goodsdetail/item26/new1_detail_07.jpg",
        "detail6":"./img/goodsdetail/item26/new1_detail_08.jpg",
        "detail7":"./img/goodsdetail/item26/new1_detail_09.jpg",
        "detail8":"./img/goodsdetail/item26/new1_detail_10.jpg"},

        {"baner1":"./img/goodsdetail/item27/new1_detail_01.jpg",
        "baner2":"./img/goodsdetail/item27/new1_detail_02.jpg",
        "detail1":"./img/goodsdetail/item27/new1_detail_03.jpg",
        "detail2":"./img/goodsdetail/item27/new1_detail_04.jpg",
        "detail3":"./img/goodsdetail/item27/new1_detail_05.jpg",
        "detail4":"./img/goodsdetail/item27/new1_detail_06.jpg",
        "detail5":"./img/goodsdetail/item27/new1_detail_07.jpg",
        "detail6":"./img/goodsdetail/item27/new1_detail_08.jpg",
        "detail7":"./img/goodsdetail/item27/new1_detail_09.jpg",
        "detail8":"./img/goodsdetail/item27/new1_detail_10.jpg"},

        {"baner1":"./img/goodsdetail/item28/new1_detail_01.jpg",
        "baner2":"./img/goodsdetail/item28/new1_detail_02.jpg",
        "detail1":"./img/goodsdetail/item28/new1_detail_03.jpg",
        "detail2":"./img/goodsdetail/item28/new1_detail_04.jpg",
        "detail3":"./img/goodsdetail/item28/new1_detail_05.jpg",
        "detail4":"./img/goodsdetail/item28/new1_detail_06.jpg",
        "detail5":"./img/goodsdetail/item28/new1_detail_07.jpg",
        "detail6":"./img/goodsdetail/item28/new1_detail_08.jpg",
        "detail7":"./img/goodsdetail/item28/new1_detail_09.jpg",
        "detail8":"./img/goodsdetail/item28/new1_detail_10.jpg"}
    ]
}